{
  "bestResult": {
    "id": "9646be92-646a-48c4-bcb6-1ed2932cfe65",
    "total_score": 49359,
    "participant_id": "3ebede6e-777d-4057-956b-50310c9fbb9e",
    "participant_name": "nghtf",
    "game_number": 9,
    "cup_id": "fe103c47-afaa-437e-804c-22b249d58672",
    "cup_name": "Кубок Соединенных Штатов Гренландии",
    "rounds": [
      {
        "round_number": 1,
        "score": 9950,
        "years_off": 1,
        "distance_meters": 1
      },
      {
        "round_number": 2,
        "score": 9947,
        "years_off": 1,
        "distance_meters": 170
      },
      {
        "round_number": 3,
        "score": 9518,
        "years_off": 3,
        "distance_meters": 3800
      },
      {
        "round_number": 4,
        "score": 9998,
        "years_off": 0,
        "distance_meters": 80
      },
      {
        "round_number": 5,
        "score": 9946,
        "years_off": 1,
        "distance_meters": 193
      }
    ]
  },
  "bestAverage": {
    "participant_id": "f77c7e02-9731-47a9-9e3e-99963b1b5caa",
    "participant_name": "GBrooklyn",
    "avg_score": 44301.3125,
    "games_played": 16
  },
  "closestDistance": {
    "distance_meters": 1,
    "round_number": 1,
    "participant_id": "3ebede6e-777d-4057-956b-50310c9fbb9e",
    "participant_name": "nghtf",
    "game_number": 3,
    "cup_id": "fe103c47-afaa-437e-804c-22b249d58672",
    "cup_name": "Кубок Соединенных Штатов Гренландии"
  },
  "bestAvgYears": {
    "participant_id": "1055519d-715b-4e13-888e-9107011d9fbb",
    "participant_name": "axnklv",
    "avg_years_off": 2.7341772151898733,
    "games_played": 16
  },
  "bestAvgDistance": {
    "participant_id": "ab3bc934-8a89-4365-a34a-796a8b5bf762",
    "participant_name": "svv1997",
    "avg_distance": 144225.96,
    "games_played": 5
  }
}